explorerApi/__init__.py
explorerApi-0.0.1.dist-info/LICENSE
explorerApi-0.0.1.dist-info/METADATA
explorerApi-0.0.1.dist-info/WHEEL
explorerApi-0.0.1.dist-info/top_level.txt
explorerApi-0.0.1.dist-info/RECORD
