Metadata-Version: 2.1
Name: explorerApi
Version: 0.0.1
Summary: Connect multiple crypto explorers API
Home-page: https://github.com/pypa/sampleproject
Author: Sau1707
Author-email: leonardo.saurwein@gmail.com
Project-URL: Bug Tracker, https://github.com/pypa/sampleproject/issues
Classifier: Programming Language :: Python :: 3
Classifier: License :: OSI Approved :: MIT License
Classifier: Operating System :: OS Independent
Requires-Python: >=3.6
License-File: LICENSE
